karrio/mappers/usps/__init__.py
karrio/mappers/usps/mapper.py
karrio/mappers/usps/proxy.py
karrio/mappers/usps/settings.py
karrio/plugins/usps/__init__.py
karrio/providers/usps/__init__.py
karrio/providers/usps/error.py
karrio/providers/usps/manifest.py
karrio/providers/usps/rate.py
karrio/providers/usps/tracking.py
karrio/providers/usps/units.py
karrio/providers/usps/utils.py
karrio/providers/usps/pickup/__init__.py
karrio/providers/usps/pickup/cancel.py
karrio/providers/usps/pickup/create.py
karrio/providers/usps/pickup/update.py
karrio/providers/usps/shipment/__init__.py
karrio/providers/usps/shipment/cancel.py
karrio/providers/usps/shipment/create.py
karrio/schemas/usps/__init__.py
karrio/schemas/usps/error_response.py
karrio/schemas/usps/label_request.py
karrio/schemas/usps/label_response.py
karrio/schemas/usps/pickup_request.py
karrio/schemas/usps/pickup_response.py
karrio/schemas/usps/pickup_update_request.py
karrio/schemas/usps/pickup_update_response.py
karrio/schemas/usps/rate_request.py
karrio/schemas/usps/rate_response.py
karrio/schemas/usps/scan_form_request.py
karrio/schemas/usps/scan_form_response.py
karrio/schemas/usps/tracking_response.py
karrio_usps-2026.1.4.dist-info/METADATA
karrio_usps-2026.1.4.dist-info/WHEEL
karrio_usps-2026.1.4.dist-info/entry_points.txt
karrio_usps-2026.1.4.dist-info/top_level.txt
karrio_usps-2026.1.4.dist-info/RECORD
